AGQueryPostgres/__init__.py
AGQueryPostgres/examples.py
AGQueryPostgres/query_json_to_sql.py
AGQueryPostgres/query_manifest.py
AGQueryPostgres/query_postgres.py
AGQueryPostgres/query_tools.py
AGQueryPostgres/query_where.py
AGQueryPostgres/security.py
AGQueryPostgres/settings.py
AGQueryPostgres-1.0.11.dist-info/LICENSE
AGQueryPostgres-1.0.11.dist-info/METADATA
AGQueryPostgres-1.0.11.dist-info/WHEEL
AGQueryPostgres-1.0.11.dist-info/top_level.txt
AGQueryPostgres-1.0.11.dist-info/RECORD
