Metadata-Version: 2.1
Name: AGQueryPostgres
Version: 1.0.11
Summary: Postgres Query Builder
Author-email: Michael Lundager <michael@wivvies.com>
License: MIT License        
Classifier: Programming Language :: Python :: 3
Classifier: License :: OSI Approved :: MIT License
Classifier: Operating System :: OS Independent
Requires-Python: >=3.7
License-File: LICENSE
Requires-Dist: AGCoder
Requires-Dist: psycopg2-binary
